headless_cms/__init__.py
headless_cms/admin.py
headless_cms/filters.py
headless_cms/forms.py
headless_cms/mixins.py
headless_cms/models.py
headless_cms/serializer_fields.py
headless_cms/serializers.py
headless_cms/settings.py
headless_cms/widgets.py
headless_cms/auto_translate/__init__.py
headless_cms/auto_translate/base_translate.py
headless_cms/auto_translate/openai_translate.py
headless_cms/contrib/__init__.py
headless_cms/contrib/astrowind/__init__.py
headless_cms/contrib/astrowind/urls.py
headless_cms/contrib/astrowind/astrowind_metadata/__init__.py
headless_cms/contrib/astrowind/astrowind_metadata/admin.py
headless_cms/contrib/astrowind/astrowind_metadata/models.py
headless_cms/contrib/astrowind/astrowind_metadata/migrations/0001_initial.py
headless_cms/contrib/astrowind/astrowind_metadata/migrations/0002_awmetadata_add_skip_translation.py
headless_cms/contrib/astrowind/astrowind_metadata/migrations/__init__.py
headless_cms/contrib/astrowind/astrowind_pages/__init__.py
headless_cms/contrib/astrowind/astrowind_pages/admin.py
headless_cms/contrib/astrowind/astrowind_pages/models.py
headless_cms/contrib/astrowind/astrowind_pages/views.py
headless_cms/contrib/astrowind/astrowind_pages/management/__init__.py
headless_cms/contrib/astrowind/astrowind_pages/management/commands/__init__.py
headless_cms/contrib/astrowind/astrowind_pages/management/commands/populate_aw_data.py
headless_cms/contrib/astrowind/astrowind_pages/migrations/0001_initial.py
headless_cms/contrib/astrowind/astrowind_pages/migrations/0002_initial.py
headless_cms/contrib/astrowind/astrowind_pages/migrations/0003_awaboutpage_add_skip_translation.py
headless_cms/contrib/astrowind/astrowind_pages/migrations/__init__.py
headless_cms/contrib/astrowind/astrowind_posts/__init__.py
headless_cms/contrib/astrowind/astrowind_posts/admin.py
headless_cms/contrib/astrowind/astrowind_posts/models.py
headless_cms/contrib/astrowind/astrowind_posts/serializers.py
django_headless_cms-1.3.0.dist-info/METADATA
django_headless_cms-1.3.0.dist-info/WHEEL
django_headless_cms-1.3.0.dist-info/licenses/LICENSE
django_headless_cms-1.3.0.dist-info/RECORD
