Metadata-Version: 2.4
Name: django-headless-cms
Version: 1.3.0
Summary: A simple django-based headless CMS.
Project-URL: Documentation, https://django-headless-cms.readthedocs.io/
Project-URL: Homepage, https://github.com/huynguyengl99/django-headless-cms
Project-URL: Repository, https://github.com/huynguyengl99/django-headless-cms
Author-email: Huy Nguyen <danghuy1999@gmail.com>
License: Copyright © 2024-present, Huy Nguyen <danghuy1999@gmail.com>.
License-File: LICENSE
Classifier: Environment :: Web Environment
Classifier: Framework :: Django
Classifier: Framework :: Django :: 4.0
Classifier: Framework :: Django :: 4.1
Classifier: Framework :: Django :: 4.2
Classifier: Framework :: Django :: 5.0
Classifier: Framework :: Django :: 5.1
Classifier: Framework :: Django :: 5.2
Classifier: Intended Audience :: Developers
Classifier: Intended Audience :: Information Technology
Classifier: License :: OSI Approved :: BSD License
Classifier: Operating System :: OS Independent
Classifier: Programming Language :: Python :: 3
Classifier: Programming Language :: Python :: 3 :: Only
Classifier: Programming Language :: Python :: 3.10
Classifier: Programming Language :: Python :: 3.11
Classifier: Programming Language :: Python :: 3.12
Classifier: Topic :: Internet :: WWW/HTTP
Classifier: Topic :: Internet :: WWW/HTTP :: Dynamic Content
Classifier: Topic :: Software Development
Classifier: Topic :: Software Development :: Libraries
Classifier: Topic :: Software Development :: Libraries :: Application Frameworks
Requires-Python: <4.0,>=3.10
Requires-Dist: django-admin-interface
Requires-Dist: django-admin-sortable2>=2.2.8
Requires-Dist: django-filter
Requires-Dist: django-import-export
Requires-Dist: django-localized-fields
Requires-Dist: django-reversion
Requires-Dist: django-solo
Requires-Dist: django<6,>=4
Requires-Dist: djangorestframework>=3
Requires-Dist: drf-spectacular
Requires-Dist: martor
Requires-Dist: psycopg
Requires-Dist: unidecode
Provides-Extra: openai
Requires-Dist: openai>=1; extra == 'openai'
